hctestbyqy111/__init__.py
hctestbyqy111/file_upload.py
hctestbyqy111/image_recognition.py
hctestbyqy111/report_screenshot.py
hctestbyqy111-0.2.3.dist-info/METADATA
hctestbyqy111-0.2.3.dist-info/WHEEL
hctestbyqy111-0.2.3.dist-info/top_level.txt
hctestbyqy111-0.2.3.dist-info/RECORD
