Metadata-Version: 2.1
Name: hctestbyqy111
Version: 0.2.3
Requires-Dist: selenium
Requires-Dist: pyautogui
Requires-Dist: opencv-python
Requires-Dist: pytesseract
Requires-Dist: allure-pytest
